snakehdl/__init__.py
snakehdl/bops.py
snakehdl/compilers/__init__.py
snakehdl/compilers/compiler.py
snakehdl/compilers/python.py
snakehdl/compilers/verilog.py
snakehdl/compilers/vhdl.py
snakehdl/components/__init__.py
snakehdl/components/arithmetic.py
snakehdl/components/logical.py
snakehdl-0.2.1.dist-info/LICENSE
snakehdl-0.2.1.dist-info/METADATA
snakehdl-0.2.1.dist-info/WHEEL
snakehdl-0.2.1.dist-info/top_level.txt
snakehdl-0.2.1.dist-info/RECORD
