Metadata-Version: 2.2
Name: snakehdl
Version: 0.2.1
Summary: A simple, purely-functional HDL for Python
Home-page: https://github.com/joshiemoore/snakehdl
Author: Josh Moore
License: MIT
Classifier: License :: OSI Approved :: MIT License
Classifier: Programming Language :: Python :: 3
Classifier: Development Status :: 3 - Alpha
Requires-Python: >=3.10
License-File: LICENSE
Requires-Dist: numpy
Requires-Dist: dill
Provides-Extra: testing
Requires-Dist: pytest; extra == "testing"
Requires-Dist: cocotb; extra == "testing"
Dynamic: author
Dynamic: classifier
Dynamic: description
Dynamic: description-content-type
Dynamic: home-page
Dynamic: license
Dynamic: provides-extra
Dynamic: requires-dist
Dynamic: requires-python
Dynamic: summary
